Metadata-Version: 2.1
Name: smallexpimv
Version: 0.0.1
Summary: A package to apply the imaginary exponential of a small-dimensional matrix to a vector.
Author-email: Tobias Jawecki <tobias.jawecki@gmail.com>
Maintainer-email: Tobias Jawecki <tobias.jawecki@gmail.com>
Project-URL: Homepage, https://github.com/newbisi/smallexpimv
Project-URL: Bug Tracker, https://github.com/newbisi/smallexpimv/issues
Keywords: matrix-exponential
Classifier: Programming Language :: Python :: 3
Classifier: License :: OSI Approved :: MIT License
Classifier: Operating System :: OS Independent
Requires-Python: >=3.7
License-File: LICENSE
